README.rst
setup.py
pyhwm2014/__init__.py
pyhwm2014.egg-info/PKG-INFO
pyhwm2014.egg-info/SOURCES.txt
pyhwm2014.egg-info/dependency_links.txt
pyhwm2014.egg-info/requires.txt
pyhwm2014.egg-info/top_level.txt
source/hwm14.f90