Metadata-Version: 1.1
Name: pyhwm2014
Version: 1.1
Summary: HWM14 neutral winds model
Home-page: https://github.com/rilma/pyHWM14
Author: ['Ronald Ilma', 'Michael Hirsch, Ph.D']
Author-email: UNKNOWN
License: UNKNOWN
Platform: UNKNOWN
Classifier: Intended Audience :: Science/Research
Classifier: Development Status :: 5 - Production/Stable
Classifier: License :: OSI Approved :: MIT License
Classifier: Topic :: Scientific/Engineering :: Atmospheric Science
Classifier: Programming Language :: Python
Classifier: Programming Language :: Python :: 3
